datasette_annotate/__init__.py
datasette_annotate/templates/annotate-row.html
datasette_annotate-0.2.1.dist-info/LICENSE
datasette_annotate-0.2.1.dist-info/METADATA
datasette_annotate-0.2.1.dist-info/WHEEL
datasette_annotate-0.2.1.dist-info/entry_points.txt
datasette_annotate-0.2.1.dist-info/top_level.txt
datasette_annotate-0.2.1.dist-info/RECORD
