Metadata-Version: 2.1
Name: datasette-annotate
Version: 0.2.1
Summary: Datasette plugin for annotating / labelling your training data.
Home-page: https://github.com/MischaU8/datasette-annotate
Author: Mischa Untaga
License: Apache License, Version 2.0
Project-URL: Issues, https://github.com/MischaU8/datasette-annotate/issues
Project-URL: CI, https://github.com/MischaU8/datasette-annotate/actions
Project-URL: Changelog, https://github.com/MischaU8/datasette-annotate/releases
Classifier: Framework :: Datasette
Classifier: License :: OSI Approved :: Apache Software License
Requires-Python: >=3.7
License-File: LICENSE
Requires-Dist: datasette (>=0.64)
Provides-Extra: test
Requires-Dist: pytest ; extra == 'test'
Requires-Dist: pytest-asyncio ; extra == 'test'
